FSM_energy_controller.v
module energy_fsm (
    input clk,
    input reset,
    input [15:0] load,
    input [15:0] solar,
    input battery_status,
    input day_flag,

    output reg solar_mode,
    output reg battery_mode,
    output reg grid_mode
);

    // -------------------------------
    // 1. State Encoding
    // -------------------------------
    parameter SOLAR      = 2'b00;
    parameter BATTERY    = 2'b01;
    parameter GRID       = 2'b10;
    parameter TRANSITION = 2'b11;

    // -------------------------------
    // 2. State Registers
    // -------------------------------
    reg [1:0] current_state, next_state; 
    reg [1:0] target_state;

    // -------------------------------
    // 3. Counter for Transition Delay
    // -------------------------------
    reg [3:0] counter;
    parameter DELAY = 4'd5;

    // -------------------------------
    // 4. State Register (Memory)
    // -------------------------------
    always @(posedge clk or posedge reset) begin
        if (reset)
            current_state <= GRID;   // safe start
        else
            current_state <= next_state;
    end

    // -------------------------------
    // 5. Counter Logic
    // -------------------------------
    always @(posedge clk or posedge reset) begin
        if (reset)
            counter <= 0;
        else if (current_state == TRANSITION)
            counter <= counter + 1;
        else
            counter <= 0;
    end

    // -------------------------------
    // 6. Next-State Logic
    // -------------------------------
    always @(*) begin
        next_state = current_state;   // default
        target_state = current_state; // default

        case (current_state)

            // -------- SOLAR STATE --------
            SOLAR: begin
                if (!day_flag)
                    target_state = (battery_status) ? BATTERY : GRID;
                else if (solar < load)
                    target_state = (battery_status) ? BATTERY : GRID;
                else
                    target_state = SOLAR;

                if (target_state != SOLAR)
                    next_state = TRANSITION;
            end

            // -------- BATTERY STATE --------
            BATTERY: begin
                if (day_flag && solar >= load)
                    target_state = SOLAR;
                else if (!battery_status)
                    target_state = GRID;
                else
                    target_state = BATTERY;

                if (target_state != BATTERY)
                    next_state = TRANSITION;
            end

            // -------- GRID STATE --------
            GRID: begin
                if (day_flag && solar >= load)
                    target_state = SOLAR;
                else if (battery_status)
                    target_state = BATTERY;
                else
                    target_state = GRID;

                if (target_state != GRID)
                    next_state = TRANSITION;
            end

            // -------- TRANSITION STATE --------
            TRANSITION: begin
                if (counter >= DELAY) begin
                    if (day_flag && solar >= load)
                        next_state = SOLAR;
                    else if (battery_status)
                        next_state = BATTERY;
                    else
                        next_state = GRID;
                end else
                    next_state = TRANSITION;
            end

        endcase
    end

    // -------------------------------
    // 7. Output Logic (Moore FSM)
    // -------------------------------
    always @(*) begin
        solar_mode = 0;
        battery_mode = 0;
        grid_mode = 0;

        case (current_state)
            SOLAR:      solar_mode = 1;
            BATTERY:    battery_mode = 1;
            GRID:       grid_mode = 1;
            TRANSITION: begin
                solar_mode = 0;
                battery_mode = 0;
                grid_mode = 0;
            end
        endcase
    end

endmodule

energy_consumption.v
module energy_consumption_calculator (
    input [15:0] total_load,
    output reg [15:0] energy_consumption,
    output reg [15:0] cost
);
parameter price_per_unit = 8; // Example price per unit energy

    always @(*) begin
        energy_consumption = total_load;
        cost = energy_consumption * price_per_unit;
    end

endmodule

load_calculation.v
//============================================================================
// LOAD CALCULATOR (APPLIANCE POWER AGGREGATOR)\n//============================================================================
// Calculates total household load by summing individual appliance demands.
// Each appliance contributes its power consumption only when ON.
//
// MODELED APPLIANCES:\n//   - AC (Air Conditioner):  1500 W (high consumption)\n//   - Fan:                     100 W\n//   - Washing Machine:         800 W (high consumption)\n//   - Bulb (Lights):           100 W\n//   - Fridge:                  200 W (continuous)\n//
// TOTAL RANGE: 0 - 2700 W max (all appliances on)\n//
// OUTPUT: total_load = sum of all (appliance power IF on_signal)\n//============================================================================

module load_calculator (
    input ac_on,
    input fan_on,
    input wm_on,         // Washing machine on/off
    input bulb_on,
    input fridge_on,
    output reg [15:0] total_load  // Total load in watts
);

    //====================================================
    // APPLIANCE LOAD AGGREGATION\n    //====================================================
    // Combinational logic: sum all active appliances
    // No clock or state required
    //====================================================
    always @(*) begin
        total_load = 16'd0;  // Initialize to zero

        // Add each appliance's power if its on_signal is active
        if (ac_on)      total_load = total_load + 16'd1500;  // A/C: high power
        if (fan_on)     total_load = total_load + 16'd100;   // Fan: medium
        if (wm_on)      total_load = total_load + 16'd800;   // Washer: high power
        if (bulb_on)    total_load = total_load + 16'd100;   // Lights: low
        if (fridge_on)  total_load = total_load + 16'd200;   // Fridge: medium
    end

endmodule

sourcecode.v
module home_energy_source_controller (
    input clk,
    input reset,
    input ac_on,
    input fan_on,
    input wm_on,
    input bulb_on,
    input fridge_on,
    input day_flag,
    input battery_status,
    input [15:0] solar_generation,
    output solar_mode,
    output battery_mode,
    output grid_mode
);

    wire [15:0] total_load;
    wire [15:0] energy_consumption;
    wire [15:0] cost;

    load_calculator load_calc (
        .ac_on(ac_on),
        .fan_on(fan_on),
        .wm_on(wm_on),
        .bulb_on(bulb_on),
        .fridge_on(fridge_on),
        .total_load(total_load)
    );

    energy_consumption_calculator energy_calc (
        .total_load(total_load),
        .energy_consumption(energy_consumption),
        .cost(cost)
    );

    energy_fsm decision_ctrl (
        .clk(clk),
        .reset(reset),
        .load(total_load),
        .solar(solar_generation),
        .battery_status(battery_status),
        .day_flag(day_flag),
        .solar_mode(solar_mode),
        .battery_mode(battery_mode),
        .grid_mode(grid_mode)
    );

endmodule

home_energy_control_tb.v
`timescale 1ns/1ps

module tb_home_energy_source_controller;

    reg clk;
    reg reset;
    reg ac_on, fan_on, wm_on, bulb_on, fridge_on;
    reg day_flag;
    reg battery_status;
    reg [2:0] case_id;

    // variable solar input
    reg [15:0] solar_input;

    wire solar_mode, battery_mode, grid_mode;

    // DUT
    home_energy_source_controller dut (
        .clk(clk),
        .reset(reset),
        .ac_on(ac_on),
        .fan_on(fan_on),
        .wm_on(wm_on),
        .bulb_on(bulb_on),
        .fridge_on(fridge_on),
        .day_flag(day_flag),
        .battery_status(battery_status),
        .solar_generation(solar_input),   
        .solar_mode(solar_mode),
        .battery_mode(battery_mode),
        .grid_mode(grid_mode)
    );

    // Clock
    initial clk = 0;
    always #5 clk = ~clk;

    // -------------------------------
    // TASK: Run Test Case
    // -------------------------------
    task run_case;
        input [8*50-1:0] name;
        input [2:0] id;
        input i_ac, i_fan, i_wm, i_bulb, i_fridge, i_day, i_batt;
        input [15:0] solar_val;
        begin
            case_id = id;
            ac_on = i_ac;
            fan_on = i_fan;
            wm_on = i_wm;
            bulb_on = i_bulb;
            fridge_on = i_fridge;
            day_flag = i_day;
            battery_status = i_batt;
            solar_input = solar_val;

            // Wait for FSM to settle and produce outputs
            repeat(10) @(posedge clk);

            // Checks
            if ((solar_mode === 1'bx) || (battery_mode === 1'bx) || (grid_mode === 1'bx))
                $display("ERROR [%0t] %0s -> X detected", $time, name);

            if ((solar_mode + battery_mode + grid_mode) != 1)
                $display("ERROR [%0t] %0s -> not one-hot S=%0b B=%0b G=%0b",
                         $time, name, solar_mode, battery_mode, grid_mode);

            // Display
            $display("[%0t] %0s | day=%0b batt=%0b load=%0d solar=%0d => S=%0b B=%0b G=%0b",
                     $time, name, day_flag, battery_status,
                     dut.total_load, solar_input,
                     solar_mode, battery_mode, grid_mode);
        end
    endtask

    // -------------------------------
    // MAIN TEST
    // -------------------------------
    initial begin

        // Dump file
        $dumpfile("home_energy_control.vcd");
        $dumpvars(0, tb_home_energy_source_controller);

        // Init
        reset = 1;
        ac_on = 0; fan_on = 0; wm_on = 0; bulb_on = 0; fridge_on = 0;
        day_flag = 0; battery_status = 0;
        solar_input = 0;

        #12;
        reset = 0;

        // -------------------------------
        // TEST CASES (WITH VARIABLE SOLAR)
        // -------------------------------

        run_case("C1: Day, no load, battery off",     1,0,0,0,0,0,1,0,16000);
        run_case("C2: Day, light load",               2,0,1,0,1,0,1,0,14000);
        run_case("C3: Day, high load, solar low",     3,1,1,1,1,1,1,1,2000);
        run_case("C4: Day, high load, no battery",    4,1,1,1,1,1,1,0,2000);
        run_case("C5: Night, medium load, battery",   5,1,1,0,1,0,0,1,0);
        run_case("C6: Night, medium load, no battery",6,1,1,0,1,0,0,0,0);
        run_case("C7: Day fluctuating solar",         7,1,0,0,1,1,1,1,10000);

        #50;
        $finish;
    end

    // -------------------------------
    // REAL-TIME MONITOR 
    // -------------------------------
    initial begin
        $monitor("Time=%0t | CS=%b NS=%b CNT=%d | S=%b B=%b G=%b",
                  $time,
                  dut.decision_ctrl.current_state,
                  dut.decision_ctrl.next_state,
                  dut.decision_ctrl.counter,
                  solar_mode, battery_mode, grid_mode);
    end

endmodule

home_energy_control.vcd
$date
	Fri Mar 20 18:24:35 2026
$end
$version
	Icarus Verilog
$end
$timescale
	1ps
$end
$scope module tb_home_energy_source_controller $end
$var wire 1 ! solar_mode $end
$var wire 1 " grid_mode $end
$var wire 1 # battery_mode $end
$var reg 1 $ ac_on $end
$var reg 1 % battery_status $end
$var reg 1 & bulb_on $end
$var reg 3 ' case_id [2:0] $end
$var reg 1 ( clk $end
$var reg 1 ) day_flag $end
$var reg 1 * fan_on $end
$var reg 1 + fridge_on $end
$var reg 1 , reset $end
$var reg 16 - solar_input [15:0] $end
$var reg 1 . wm_on $end
$scope module dut $end
$var wire 1 $ ac_on $end
$var wire 1 % battery_status $end
$var wire 1 & bulb_on $end
$var wire 1 ( clk $end
$var wire 1 ) day_flag $end
$var wire 1 * fan_on $end
$var wire 1 + fridge_on $end
$var wire 1 , reset $end
$var wire 16 / solar_generation [15:0] $end
$var wire 1 . wm_on $end
$var wire 16 0 total_load [15:0] $end
$var wire 1 ! solar_mode $end
$var wire 1 " grid_mode $end
$var wire 16 1 energy_consumption [15:0] $end
$var wire 16 2 cost [15:0] $end
$var wire 1 # battery_mode $end
$scope module decision_ctrl $end
$var wire 1 % battery_status $end
$var wire 1 ( clk $end
$var wire 1 ) day_flag $end
$var wire 1 , reset $end
$var wire 16 3 solar [15:0] $end
$var wire 16 4 load [15:0] $end
$var parameter 2 5 BATTERY $end
$var parameter 4 6 DELAY $end
$var parameter 2 7 GRID $end
$var parameter 2 8 SOLAR $end
$var parameter 2 9 TRANSITION $end
$var reg 1 # battery_mode $end
$var reg 4 : counter [3:0] $end
$var reg 2 ; current_state [1:0] $end
$var reg 1 " grid_mode $end
$var reg 2 < next_state [1:0] $end
$var reg 1 ! solar_mode $end
$var reg 2 = target_state [1:0] $end
$upscope $end
$scope module energy_calc $end
$var wire 16 > total_load [15:0] $end
$var parameter 32 ? price_per_unit $end
$var reg 16 @ cost [15:0] $end
$var reg 16 A energy_consumption [15:0] $end
$upscope $end
$scope module load_calc $end
$var wire 1 $ ac_on $end
$var wire 1 & bulb_on $end
$var wire 1 * fan_on $end
$var wire 1 + fridge_on $end
$var wire 1 . wm_on $end
$var reg 16 B total_load [15:0] $end
$upscope $end
$upscope $end
$scope task run_case $end
$var reg 1 C i_ac $end
$var reg 1 D i_batt $end
$var reg 1 E i_bulb $end
$var reg 1 F i_day $end
$var reg 1 G i_fan $end
$var reg 1 H i_fridge $end
$var reg 1 I i_wm $end
$var reg 3 J id [2:0] $end
$var reg 400 K name [399:0] $end
$var reg 16 L solar_val [15:0] $end
$upscope $end
$upscope $end
$enddefinitions $end
$comment Show the parameter values. $end
$dumpall
b1000 ?
b11 9
b0 8
b10 7
b101 6
b1 5
$end
#0
$dumpvars
bx L
bx K
bx J
xI
xH
xG
xF
xE
xD
xC
b0 B
b0 A
b0 @
b0 >
b10 =
b10 <
b10 ;
b0 :
b0 4
b0 3
b0 2
b0 1
b0 0
b0 /
0.
b0 -
1,
0+
0*
0)
0(
bx '
0&
0%
0$
0#
1"
0!
$end
#5000
1(
#10000
0(
#12000
b11 <
b0 =
b11111010000000 -
b11111010000000 /
b11111010000000 3
1)
b1 '
b11111010000000 L
0D
1F
0H
0E
0I
0G
0C
b1 J
b100001100110001001110100010000001000100011000010111100100101100001000000110111001101111001000000110110001101111011000010110010000101100001000000110001001100001011101000111010001100101011100100111100100100000011011110110011001100110 K
0,
#15000
0"
b11 =
b11 ;
1(
#20000
0(
#25000
b1 :
1(
#30000
0(
#35000
b10 :
1(
#40000
0(
#45000
b11 :
1(
#50000
0(
#55000
b100 :
1(
#60000
0(
#65000
b0 <
b101 :
1(
#70000
0(
#75000
1!
b0 =
b0 ;
b110 :
1(
#80000
0(
#85000
b0 :
1(
#90000
0(
#95000
1(
#100000
0(
#105000
b100101100000 2
b100101100000 @
b100101100 1
b100101100 A
b100101100 0
b100101100 4
b100101100 >
b100101100 B
b11011010110000 -
b11011010110000 /
b11011010110000 3
1&
1*
b10 '
b11011010110000 L
1E
1G
b10 J
b1000011001100100011101000100000010001000110000101111001001011000010000001101100011010010110011101101000011101000010000001101100011011110110000101100100 K
1(
#110000
0(
#115000
1(
#120000
0(
#125000
1(
#130000
0(
#135000
1(
#140000
0(
#145000
1(
#150000
0(
#155000
1(
#160000
0(
#165000
1(
#170000
0(
#175000
1(
#180000
0(
#185000
1(
#190000
0(
#195000
1(
#200000
0(
#205000
b101000101000000 2
b101000101000000 @
b101000101000 1
b101000101000 A
b11 <
b1 =
b101000101000 0
b101000101000 4
b101000101000 >
b101000101000 B
b11111010000 -
b11111010000 /
b11111010000 3
1%
1+
1.
1$
b11 '
b11111010000 L
1D
1H
1I
1C
b11 J
b100001100110011001110100010000001000100011000010111100100101100001000000110100001101001011001110110100000100000011011000110111101100001011001000010110000100000011100110110111101101100011000010111001000100000011011000110111101110111 K
1(
#210000
0(
#215000
0!
b11 =
b11 ;
1(
#220000
0(
#225000
b1 :
1(
#230000
0(
#235000
b10 :
1(
#240000
0(
#245000
b11 :
1(
#250000
0(
#255000
b100 :
1(
#260000
0(
#265000
b1 <
b101 :
1(
#270000
0(
#275000
1#
b1 =
b1 ;
b110 :
1(
#280000
0(
#285000
b0 :
1(
#290000
0(
#295000
1(
#300000
0(
#305000
b11 <
b10 =
0%
b100 '
0D
b100 J
b10000110011010000111010001000000100010001100001011110010010110000100000011010000110100101100111011010000010000001101100011011110110000101100100001011000010000001101110011011110010000001100010011000010111010001110100011001010111001001111001 K
1(
#310000
0(
#315000
0#
b11 =
b11 ;
1(
#320000
0(
#325000
b1 :
1(
#330000
0(
#335000
b10 :
1(
#340000
0(
#345000
b11 :
1(
#350000
0(
#355000
b100 :
1(
#360000
0(
#365000
b10 <
b101 :
1(
#370000
0(
#375000
1"
b10 =
b10 ;
b110 :
1(
#380000
0(
#385000
b0 :
1(
#390000
0(
#395000
1(
#400000
0(
#405000
b11100001000000 2
b11100001000000 @
b11100001000 1
b11100001000 A
b11 <
b1 =
b11100001000 0
b11100001000 4
b11100001000 >
b11100001000 B
b0 -
b0 /
b0 3
1%
0)
0+
0.
b101 '
b0 L
1D
0F
0H
0I
b101 J
b1000011001101010011101000100000010011100110100101100111011010000111010000101100001000000110110101100101011001000110100101110101011011010010000001101100011011110110000101100100001011000010000001100010011000010111010001110100011001010111001001111001 K
1(
#410000
0(
#415000
0"
b11 =
b11 ;
1(
#420000
0(
#425000
b1 :
1(
#430000
0(
#435000
b10 :
1(
#440000
0(
#445000
b11 :
1(
#450000
0(
#455000
b100 :
1(
#460000
0(
#465000
b1 <
b101 :
1(
#470000
0(
#475000
1#
b1 =
b1 ;
b110 :
1(
#480000
0(
#485000
b0 :
1(
#490000
0(
#495000
1(
#500000
0(
#505000
b11 <
b10 =
0%
b110 '
0D
b110 J
b1000011001101100011101000100000010011100110100101100111011010000111010000101100001000000110110101100101011001000110100101110101011011010010000001101100011011110110000101100100001011000010000001101110011011110010000001100010011000010111010001110100011001010111001001111001 K
1(
#510000
0(
#515000
0#
b11 =
b11 ;
1(
#520000
0(
#525000
b1 :
1(
#530000
0(
#535000
b10 :
1(
#540000
0(
#545000
b11 :
1(
#550000
0(
#555000
b100 :
1(
#560000
0(
#565000
b10 <
b101 :
1(
#570000
0(
#575000
1"
b10 =
b10 ;
b110 :
1(
#580000
0(
#585000
b0 :
1(
#590000
0(
#595000
1(
#600000
0(
#605000
b11101101100000 2
b11101101100000 @
b11101101100 1
b11101101100 A
b11 <
b0 =
b11101101100 0
b11101101100 4
b11101101100 >
b11101101100 B
b10011100010000 -
b10011100010000 /
b10011100010000 3
1%
1)
1+
0*
b111 '
b10011100010000 L
1D
1F
1H
0G
b111 J
b1000011001101110011101000100000010001000110000101111001001000000110011001101100011101010110001101110100011101010110000101110100011010010110111001100111001000000111001101101111011011000110000101110010 K
1(
#610000
0(
#615000
0"
b11 =
b11 ;
1(
#620000
0(
#625000
b1 :
1(
#630000
0(
#635000
b10 :
1(
#640000
0(
#645000
b11 :
1(
#650000
0(
#655000
b100 :
1(
#660000
0(
#665000
b0 <
b101 :
1(
#670000
0(
#675000
1!
b0 =
b0 ;
b110 :
1(
#680000
0(
#685000
b0 :
1(
