power_mode.v

module energy_source_controller (
    input [15:0] total_load,
    input [15:0] solar_generation,  
    input battery_status,
    input day_flag,          // 1 = day, 0 = night

    output reg solar_mode,  
    output reg battery_mode,
    output reg grid_mode
);

always @(*) 
begin
    // default values
    solar_mode = 0;
    battery_mode = 0;
    grid_mode = 0;

    // DAYTIME LOGIC
    if (day_flag == 1) 
    begin
        if (solar_generation >= total_load)
            solar_mode = 1;      // solar sufficient
        else if (battery_status)
            battery_mode = 1;    // use battery
        else
            grid_mode = 1;       // fallback to grid
    end
    
    // NIGHT LOGIC
    else 
    begin
        if (battery_status)
            battery_mode = 1;    // battery at night
        else
            grid_mode = 1;       // grid if battery low
    end

end

endmodule

energy_consumption.v
module energy_consumption_calculator (
    input [15:0] total_load,
    output reg [15:0] energy_consumption,
    output reg [15:0] cost
);
parameter price_per_unit = 8; // Example price per unit energy

    always @(*) begin
        energy_consumption = total_load;
        cost = energy_consumption * price_per_unit;
    end

endmodule

load_calculation.v
//============================================================================
// LOAD CALCULATOR (APPLIANCE POWER AGGREGATOR)\n//============================================================================
// Calculates total household load by summing individual appliance demands.
// Each appliance contributes its power consumption only when ON.
//
// MODELED APPLIANCES:\n//   - AC (Air Conditioner):  1500 W (high consumption)\n//   - Fan:                     100 W\n//   - Washing Machine:         800 W (high consumption)\n//   - Bulb (Lights):           100 W\n//   - Fridge:                  200 W (continuous)\n//
// TOTAL RANGE: 0 - 2700 W max (all appliances on)\n//
// OUTPUT: total_load = sum of all (appliance power IF on_signal)\n//============================================================================

module load_calculator (
    input ac_on,
    input fan_on,
    input wm_on,         // Washing machine on/off
    input bulb_on,
    input fridge_on,
    output reg [15:0] total_load  // Total load in watts
);

    //====================================================
    // APPLIANCE LOAD AGGREGATION\n    //====================================================
    // Combinational logic: sum all active appliances
    // No clock or state required
    //====================================================
    always @(*) begin
        total_load = 16'd0;  // Initialize to zero

        // Add each appliance's power if its on_signal is active
        if (ac_on)      total_load = total_load + 16'd1500;  // A/C: high power
        if (fan_on)     total_load = total_load + 16'd100;   // Fan: medium
        if (wm_on)      total_load = total_load + 16'd800;   // Washer: high power
        if (bulb_on)    total_load = total_load + 16'd100;   // Lights: low
        if (fridge_on)  total_load = total_load + 16'd200;   // Fridge: medium
    end

endmodule

sourcecode.v
module home_energy_source_controller (
    input clk,
    input reset, 
    input ac_on,
    input fan_on,
    input wm_on,
    input bulb_on,
    input fridge_on, 
    input day_flag,
    input battery_status,

    input [15:0] solar_generation,   

    output solar_mode,
    output battery_mode,
    output grid_mode
);

    wire [15:0] total_load;
    wire [15:0] energy_consumption;
    wire [15:0] cost;

    // Load calculation
    load_calculator load_calc (
        .ac_on(ac_on),
        .fan_on(fan_on),
        .wm_on(wm_on),
        .bulb_on(bulb_on),
        .fridge_on(fridge_on),
        .total_load(total_load)
    );

    // Energy calculation
    energy_consumption_calculator energy_calc (
        .total_load(total_load),
        .energy_consumption(energy_consumption),
        .cost(cost)
    );

    // FSM Controller
    energy_source_controller decision_ctrl (
        .total_load(total_load),
        .solar_generation(solar_generation),
        .battery_status(battery_status),
        .day_flag(day_flag),
        .solar_mode(solar_mode),
        .battery_mode(battery_mode),
        .grid_mode(grid_mode)
    );

endmodule

home_energy_control_tb.v

`timescale 1ns/1ps

module tb_home_energy_source_controller;

    reg clk;
    reg reset;
    reg ac_on, fan_on, wm_on, bulb_on, fridge_on;
    reg day_flag;
    reg battery_status;
    reg [2:0] case_id;

    wire solar_mode, battery_mode, grid_mode;

    // DUT
    home_energy_source_controller dut (
        .clk(clk),
        .reset(reset),
        .ac_on(ac_on),
        .fan_on(fan_on),
        .wm_on(wm_on),
        .bulb_on(bulb_on),
        .fridge_on(fridge_on),
        .day_flag(day_flag),
        .battery_status(battery_status),
        .solar_mode(solar_mode),
        .battery_mode(battery_mode),
        .grid_mode(grid_mode)
    );

    // Clock (even if currently unused)
    initial clk = 0;
    always #5 clk = ~clk;

    task run_case;
        input [8*40-1:0] name;
        input [2:0] id;
        input i_ac, i_fan, i_wm, i_bulb, i_fridge, i_day, i_batt;
        begin
            case_id = id;
            ac_on = i_ac;
            fan_on = i_fan;
            wm_on = i_wm;
            bulb_on = i_bulb;
            fridge_on = i_fridge;
            day_flag = i_day;
            battery_status = i_batt;

            #10; // wait for combinational settle

            // Basic validity checks
            if ((solar_mode === 1'bx) || (battery_mode === 1'bx) || (grid_mode === 1'bx))
                $display("ERROR [%0t] %0s -> X detected in outputs", $time, name);

            if ((solar_mode + battery_mode + grid_mode) != 1)
                $display("ERROR [%0t] %0s -> outputs not one-hot: S=%0b B=%0b G=%0b",
                         $time, name, solar_mode, battery_mode, grid_mode);

            $display("[%0t] %0s | day=%0b batt=%0b load=%0d solar_gen=%0d cost=%0d => S=%0b B=%0b G=%0b",
                     $time, name, day_flag, battery_status,
                     dut.total_load, dut.solar_generation, dut.cost,
                     solar_mode, battery_mode, grid_mode);
        end
    endtask

    initial begin
        // Generate waveform dump for GTKWave
        $dumpfile("home_energy_control.vcd");
        $dumpvars(0, tb_home_energy_source_controller);

        // Init
        reset = 1;
        ac_on = 0; fan_on = 0; wm_on = 0; bulb_on = 0; fridge_on = 0;
        day_flag = 0; battery_status = 0;
        case_id = 0;

        #12;
        reset = 0;

        // Test scenarios
        run_case("C1: Day, no load, battery off",     1,0,0,0,0,0,1,0);
        run_case("C2: Day, light load, battery off",  2,0,1,0,1,0,1,0);
        run_case("C3: Day, high load, battery on",    3,1,1,1,1,1,1,1);
        run_case("C4: Day, high load, battery off",   4,1,1,1,1,1,1,0);
        run_case("C5: Night, medium load, battery on",5,1,1,0,1,0,0,1);
        run_case("C6: Night, medium load, battery off",6,1,1,0,1,0,0,0);
        run_case("C7: Night, no load, battery on",    7,0,0,0,0,0,0,1);

        #20;
        $finish;
    end

endmodule

home_energy_control.vcd
$date
	Sat Mar 14 13:10:48 2026
$end
$version
	Icarus Verilog
$end
$timescale
	1ps
$end
$scope module tb_home_energy_source_controller $end
$var wire 1 ! solar_mode $end
$var wire 1 " grid_mode $end
$var wire 1 # battery_mode $end
$var reg 1 $ ac_on $end
$var reg 1 % battery_status $end
$var reg 1 & bulb_on $end
$var reg 3 ' case_id [2:0] $end
$var reg 1 ( clk $end
$var reg 1 ) day_flag $end
$var reg 1 * fan_on $end
$var reg 1 + fridge_on $end
$var reg 1 , reset $end
$var reg 1 - wm_on $end
$scope module dut $end
$var wire 1 $ ac_on $end
$var wire 1 % battery_status $end
$var wire 1 & bulb_on $end
$var wire 1 ( clk $end
$var wire 1 ) day_flag $end
$var wire 1 * fan_on $end
$var wire 1 + fridge_on $end
$var wire 1 , reset $end
$var wire 1 - wm_on $end
$var wire 16 . total_load [15:0] $end
$var wire 1 ! solar_mode $end
$var wire 16 / solar_generation [15:0] $end
$var wire 1 " grid_mode $end
$var wire 16 0 energy_consumption [15:0] $end
$var wire 16 1 cost [15:0] $end
$var wire 1 # battery_mode $end
$scope module decision_ctrl $end
$var wire 1 % battery_status $end
$var wire 1 ) day_flag $end
$var wire 16 2 total_load [15:0] $end
$var wire 16 3 solar_generation [15:0] $end
$var reg 1 # battery_mode $end
$var reg 1 " grid_mode $end
$var reg 1 ! solar_mode $end
$upscope $end
$scope module energy_calc $end
$var wire 16 4 total_load [15:0] $end
$var parameter 32 5 price_per_unit $end
$var reg 16 6 cost [15:0] $end
$var reg 16 7 energy_consumption [15:0] $end
$upscope $end
$scope module load_calc $end
$var wire 1 $ ac_on $end
$var wire 1 & bulb_on $end
$var wire 1 * fan_on $end
$var wire 1 + fridge_on $end
$var wire 1 - wm_on $end
$var reg 16 8 total_load [15:0] $end
$upscope $end
$scope module solar_calc $end
$var wire 1 ) day_flag $end
$var reg 16 9 solar_generation [15:0] $end
$upscope $end
$upscope $end
$scope task run_case $end
$var reg 1 : i_ac $end
$var reg 1 ; i_batt $end
$var reg 1 < i_bulb $end
$var reg 1 = i_day $end
$var reg 1 > i_fan $end
$var reg 1 ? i_fridge $end
$var reg 1 @ i_wm $end
$var reg 3 A id [2:0] $end
$var reg 320 B name [319:0] $end
$upscope $end
$upscope $end
$enddefinitions $end
$comment Show the parameter values. $end
$dumpall
b1000 5
$end
#0
$dumpvars
bx B
bx A
x@
x?
x>
x=
x<
x;
x:
b0 9
b0 8
b0 7
b0 6
b0 4
b0 3
b0 2
b0 1
b0 0
b0 /
b0 .
0-
1,
0+
0*
0)
0(
b0 '
0&
0%
0$
0#
1"
0!
$end
#5000
1(
#10000
0(
#12000
1!
0"
b11111010000000 /
b11111010000000 3
b11111010000000 9
1)
b1 '
0;
1=
0?
0<
0@
0>
0:
b1 A
b100001100110001001110100010000001000100011000010111100100101100001000000110111001101111001000000110110001101111011000010110010000101100001000000110001001100001011101000111010001100101011100100111100100100000011011110110011001100110 B
0,
#15000
1(
#20000
0(
#22000
1!
b100101100000 1
b100101100000 6
b100101100 0
b100101100 7
b100101100 .
b100101100 2
b100101100 4
b100101100 8
1&
1*
b10 '
1<
1>
b10 A
b100001100110010001110100010000001000100011000010111100100101100001000000110110001101001011001110110100001110100001000000110110001101111011000010110010000101100001000000110001001100001011101000111010001100101011100100111100100100000011011110110011001100110 B
#25000
1(
#30000
0(
#32000
b101000101000000 1
b101000101000000 6
b101000101000 0
b101000101000 7
1!
b101000101000 .
b101000101000 2
b101000101000 4
b101000101000 8
1%
1+
1-
1$
b11 '
1;
1?
1@
1:
b11 A
b10000110011001100111010001000000100010001100001011110010010110000100000011010000110100101100111011010000010000001101100011011110110000101100100001011000010000001100010011000010111010001110100011001010111001001111001001000000110111101101110 B
#35000
1(
#40000
0(
#42000
1!
0%
b100 '
0;
b100 A
b1000011001101000011101000100000010001000110000101111001001011000010000001101000011010010110011101101000001000000110110001101111011000010110010000101100001000000110001001100001011101000111010001100101011100100111100100100000011011110110011001100110 B
#45000
1(
#50000
0(
#52000
b11100001000000 1
b11100001000000 6
b11100001000 0
b11100001000 7
1#
0!
b0 /
b0 3
b0 9
b11100001000 .
b11100001000 2
b11100001000 4
b11100001000 8
1%
0)
0+
0-
b101 '
1;
0=
0?
0@
b101 A
b1000011001101010011101000100000010011100110100101100111011010000111010000101100001000000110110101100101011001000110100101110101011011010010000001101100011011110110000101100100001011000010000001100010011000010111010001110100011001010111001001111001001000000110111101101110 B
#55000
1(
#60000
0(
#62000
1"
0#
0%
b110 '
0;
b110 A
b100001100110110001110100010000001001110011010010110011101101000011101000010110000100000011011010110010101100100011010010111010101101101001000000110110001101111011000010110010000101100001000000110001001100001011101000111010001100101011100100111100100100000011011110110011001100110 B
#65000
1(
#70000
0(
#72000
b0 1
b0 6
b0 0
b0 7
1#
0"
b0 .
b0 2
b0 4
b0 8
1%
0&
0*
0$
b111 '
1;
0<
0>
0:
b111 A
b10000110011011100111010001000000100111001101001011001110110100001110100001011000010000001101110011011110010000001101100011011110110000101100100001011000010000001100010011000010111010001110100011001010111001001111001001000000110111101101110 B
